{
  "stage": 9,
  "stage_result": [
    "Vd Poel",
    "T.H. Johannessen",
    "T. Pidcock",
    "Baudin",
    "F. Ganna",
    "Pedersen",
    "M. Matthews",
    "Breuillard",
    "Jegat",
    "Quinn"
  ],
  "gc": [
    "Pogacar",
    "Vingegaard",
    "Del Torro Romero",
    "Evenepoel",
    "Ayuso"
  ],
  "points": [
    "Pedersen",
    "Girmay",
    "T. Merlier"
  ],
  "mountains": [
    "Pogacar",
    "Vingegaard",
    "L. Martinez"
  ],
  "youth": [
    "Del Torro Romero",
    "Ayuso",
    "P. Seixas"
  ]
}